nonebot_plugin_df_armor_database/__init__.py
nonebot_plugin_df_armor_database-0.0.1.dist-info/LICENSE
nonebot_plugin_df_armor_database-0.0.1.dist-info/METADATA
nonebot_plugin_df_armor_database-0.0.1.dist-info/WHEEL
nonebot_plugin_df_armor_database-0.0.1.dist-info/RECORD
